LICENSE
README.md
setup.py
cloud_import/__init__.py
cloud_import/cloud_import.py
cloud_import.egg-info/PKG-INFO
cloud_import.egg-info/SOURCES.txt
cloud_import.egg-info/dependency_links.txt
cloud_import.egg-info/requires.txt
cloud_import.egg-info/top_level.txt